newrelic_asyncpg/__init__.py
newrelic_asyncpg-0.1.3.dist-info/LICENSE
newrelic_asyncpg-0.1.3.dist-info/METADATA
newrelic_asyncpg-0.1.3.dist-info/WHEEL
newrelic_asyncpg-0.1.3.dist-info/entry_points.txt
newrelic_asyncpg-0.1.3.dist-info/top_level.txt
newrelic_asyncpg-0.1.3.dist-info/RECORD
